wechat_qr_detection/__init__.py
wechat_qr_detection/logo.png
wechat_qr_detection/utils.py
wechat_qr_detection-0.0.8.dist-info/LICENSE
wechat_qr_detection-0.0.8.dist-info/METADATA
wechat_qr_detection-0.0.8.dist-info/WHEEL
wechat_qr_detection-0.0.8.dist-info/top_level.txt
wechat_qr_detection-0.0.8.dist-info/RECORD
